__init__.py
main.py
22BEE0040-0.0.2.dist-info/LICENSE
22BEE0040-0.0.2.dist-info/METADATA
22BEE0040-0.0.2.dist-info/WHEEL
22BEE0040-0.0.2.dist-info/top_level.txt
22BEE0040-0.0.2.dist-info/RECORD
