Metadata-Version: 2.1
Name: 22BEE0040
Version: 0.0.2
Summary: A small package which does addition, subtraction, multiplication and division of two whole numbers.
Author-email: Aahir Basu <aahir.basu2022@vitstudent.ac.in>
Classifier: Programming Language :: Python :: 3
Classifier: License :: OSI Approved :: MIT License
Classifier: Operating System :: OS Independent
Requires-Python: >=3.7
License-File: LICENSE
